auto_video_mcp/__init__.py
auto_video_mcp/server.py
auto_video_mcp/tools/__init__.py
auto_video_mcp/tools/audio_tools.py
auto_video_mcp/tools/autohome.py
auto_video_mcp/tools/avatar_tools.py
auto_video_mcp/tools/baidu.py
auto_video_mcp/tools/crawlweb.py
auto_video_mcp/tools/custom_rss.py
auto_video_mcp/tools/kr36.py
auto_video_mcp/tools/query_tools.py
auto_video_mcp/tools/video_tools.py
auto_video_mcp/tools/voice_tools.py
auto_video_mcp/tools/websearch.py
auto_video_mcp/utils/api_client.py
auto_video_mcp/utils/cache.py
auto_video_mcp/utils/config.py
auto_video_mcp/utils/database.py
auto_video_mcp/utils/http.py
auto_video_mcp/utils/logger.py
auto_video_mcp/utils/migrations.py
auto_video_mcp/utils/models.py
auto_video_mcp/utils/rss.py
auto_video_mcp/utils/task_manager.py
auto_video_mcp-0.1.1.dist-info/METADATA
auto_video_mcp-0.1.1.dist-info/WHEEL
auto_video_mcp-0.1.1.dist-info/entry_points.txt
auto_video_mcp-0.1.1.dist-info/top_level.txt
auto_video_mcp-0.1.1.dist-info/RECORD
