Metadata-Version: 2.4
Name: auto_video_mcp
Version: 0.1.1
Summary: 飞影数字人API服务，提供数字人相关功能
Home-page: https://github.com/fancyboi999/auto_video_mcp
Author-email: fancy <fancyboi999@gmail.com>
License-Expression: MIT
Project-URL: Homepage, https://github.com/fancyboi999/auto_video_mcp
Project-URL: Bug Tracker, https://github.com/fancyboi999/auto_video_mcp/issues
Project-URL: Documentation, https://github.com/fancyboi999/auto_video_mcp/docs
Classifier: Programming Language :: Python :: 3
Classifier: Programming Language :: Python :: 3.11
Classifier: Operating System :: OS Independent
Requires-Python: >=3.11
Requires-Dist: fastapi>=0.110.0
Requires-Dist: fastmcp>=1.6.0
Requires-Dist: pydantic>=2.11.3
Requires-Dist: requests>=2.32.3
Requires-Dist: aiosqlite>=0.21.0
Requires-Dist: uvicorn>=0.34.2
Requires-Dist: greenlet>=3.2.3
Requires-Dist: sqlalchemy>=2.0.30
Requires-Dist: alembic
Requires-Dist: asyncpg>=0.30.0
Requires-Dist: python-dotenv>=1.1.0
Requires-Dist: firecrawl>=0.1.0
Requires-Dist: httpx>=0.25.0
Requires-Dist: lxml>=4.9.0
Requires-Dist: beautifulsoup4>=4.11.0
Requires-Dist: python-dateutil>=2.8.0
Requires-Dist: feedparser>=6.0.0
Provides-Extra: dev
Requires-Dist: build>=1.2.2.post1; extra == "dev"
Requires-Dist: setuptools>=45; extra == "dev"
Requires-Dist: twine>=6.1.0; extra == "dev"
Dynamic: home-page
Dynamic: requires-python
